{
  "lang": "cs",
  "title": "Тест рівня володіння чеською мовою A1–C2 (CEFR)",
  "questions": [
    {"id":"A1-1","level":"A1","q":"Як чеською сказати «Добрий день» у ввічливій формі?","options":["Ahoj","Dobrý den","Čau","Nazdar","Не знаю"],"answerIdx":1},
    {"id":"A1-2","level":"A1","q":"Оберіть правильний переклад речення «Я студент».","options":["Já jsem student.","Já je student.","Já být student.","Jsem studenti.","Не знаю"],"answerIdx":0},
    {"id":"A1-3","level":"A1","q":"Як чеською буде запитання «Як тебе звати?»","options":["Jak se jmenuješ?","Kde jsi?","Kdo jsi?","Kolik máš?","Не знаю"],"answerIdx":0},
    {"id":"A1-4","level":"A1","q":"Слово «dům» означає:","options":["дім","автомобіль","вікно","стілець","Не знаю"],"answerIdx":0},
    {"id":"A1-5","level":"A1","q":"Як подякувати чеською?","options":["Prosím","Díky","Na shledanou","Promiňte","Не знаю"],"answerIdx":1},
    {"id":"A1-6","level":"A1","q":"Як сказати чеською «Я живу у Празі»?","options":["Bydlím v Praze.","Bydlet Praha.","Já bydlí Praha.","Bydlím Praha.","Не знаю"],"answerIdx":0},
    {"id":"A1-7","level":"A1","q":"Як запитати «Звідки ти?»","options":["Odkud jsi?","Kde jsi?","Kam jdeš?","Kdo jsi?","Не знаю"],"answerIdx":0},
    {"id":"A1-8","level":"A1","q":"Що означає слово «čaj»?","options":["кава","сік","чай","молоко","Не знаю"],"answerIdx":2},

    {"id":"A2-1","level":"A2","q":"Як перекласти: «Я працюю в офісі»?","options":["Pracuji v kanceláři.","Já práce kancelář.","Pracuju do kancelář.","Pracoval kancelář.","Не знаю"],"answerIdx":0},
    {"id":"A2-2","level":"A2","q":"Оберіть правильну форму минулого часу: «Я їв».","options":["Jedl jsem.","Jím.","Jíst.","Jedla.","Не знаю"],"answerIdx":0},
    {"id":"A2-3","level":"A2","q":"Як сказати: «Мені подобається Прага».","options":["Mám rád Prahu.","Líbí mě Praha.","Líbím Praha.","Praha mě má ráda.","Не знаю"],"answerIdx":0},
    {"id":"A2-4","level":"A2","q":"Як сказати: «Я повинен іти».","options":["Musím jít.","Můžu jít.","Chci jít.","Šel bych.","Не знаю"],"answerIdx":0},
    {"id":"A2-5","level":"A2","q":"Слово «dobrý» означає:","options":["добрий","поганий","повільний","старий","Не знаю"],"answerIdx":0},
    {"id":"A2-6","level":"A2","q":"Як сказати: «У мене немає часу».","options":["Nemám čas.","Mám čas.","Budu mít čas.","Měl jsem čas.","Не знаю"],"answerIdx":0},
    {"id":"A2-7","level":"A2","q":"Що означає фраза «Jak se máš?»","options":["Як справи?","Де ти?","Що робиш?","Хто ти?","Не знаю"],"answerIdx":0},
    {"id":"A2-8","level":"A2","q":"Як сказати чеською «Мені потрібно купити хліб».","options":["Potřebuji koupit chleba.","Mám koupit chléb.","Kupuju chleba.","Chci chléb.","Не знаю"],"answerIdx":0},

    {"id":"B1-1","level":"B1","q":"Що означає сполучник «protože»?","options":["тому що","через це","хоча","коли","Не знаю"],"answerIdx":0},
    {"id":"B1-2","level":"B1","q":"Як сказати: «Я думаю, що він прийде».","options":["Myslím, že přijde.","Myslím přijde.","Myslím, on přijde.","Přijde, myslím.","Не знаю"],"answerIdx":0},
    {"id":"B1-3","level":"B1","q":"Як сказати: «Я хотів би кави».","options":["Chtěl bych kávu.","Chci kávу.","Mám rád kávу.","Dám si kávу.","Не знаю"],"answerIdx":0},
    {"id":"B1-4","level":"B1","q":"Як перекласти: «Якщо буде дощ, я залишусь удома».","options":["Když bude pršet, zůstanu doma.","Protože prší, jsem doma.","Pršelo, zůstanu doma.","Zůstanu doma, kdy prší.","Не знаю"],"answerIdx":0},
    {"id":"B1-5","level":"B1","q":"Слово «nikdy» означає:","options":["ніколи","завжди","іноді","рідко","Не знаю"],"answerIdx":0},
    {"id":"B1-6","level":"B1","q":"Як перекласти речення «On umí plavat».","options":["Він уміє плавати","Він хоче плавати","Він любить плавати","Він не вміє плавати","Не знаю"],"answerIdx":0},
    {"id":"B1-7","level":"B1","q":"Фраза «mít rád» означає:","options":["любити","мати","знати","бути","Не знаю"],"answerIdx":0},
    {"id":"B1-8","level":"B1","q":"Як сказати: «Він старший за мене».","options":["Je starší než já.","Je starý jako já.","Je starší já.","Starší jsem já.","Не знаю"],"answerIdx":0},

    {"id":"B2-1","level":"B2","q":"Що означає вираз «i když»?","options":["навіть якщо","тому що","тому","поки","Не знаю"],"answerIdx":0},
    {"id":"B2-2","level":"B2","q":"Як сказати: «Він сказав, що не знає».","options":["Řekl, že neví.","Řekl, neví.","On říká, že nevím.","Říká, že neví.","Не знаю"],"answerIdx":0},
    {"id":"B2-3","level":"B2","q":"Синонім слова «přesto».","options":["все ж","тому що","отже","коли","Не знаю"],"answerIdx":0},
    {"id":"B2-4","level":"B2","q":"Як сказати: «Я звик рано вставати».","options":["Jsem zvyklý vstávat brzy.","Mám rád vstávat.","Chci vstávat.","Rád vstávám.","Не знаю"],"answerIdx":0},
    {"id":"B2-5","level":"B2","q":"Як перекласти: «Беручи до уваги ситуацію».","options":["S ohledem na situaci.","Podle situace.","Kvůli situaci.","Vzhledem situaci.","Не знаю"],"answerIdx":0},
    {"id":"B2-6","level":"B2","q":"Фраза «během dne» означає:","options":["протягом дня","через день","удень","на день","Не знаю"],"answerIdx":0},
    {"id":"B2-7","level":"B2","q":"Що означає слово «přestože»?","options":["незважаючи на те, що","оскільки","якщо","коли","Не знаю"],"answerIdx":0},
    {"id":"B2-8","level":"B2","q":"Як сказати: «У порівнянні з…».","options":["ve srovnání s","na rozdíl od","kvůli","místo","Не знаю"],"answerIdx":0},

    {"id":"C1-1","level":"C1","q":"Що означає вираз «brát něco v úvahu»?","options":["брати до уваги","забувати","ігнорувати","пропонувати","Не знаю"],"answerIdx":0},
    {"id":"C1-2","level":"C1","q":"Як сказати: «Я схильний думати, що…».","options":["Mám sklon myslet si, že...","Chci myslet, že...","Myslím, že to je...","Rád myslím, že...","Не знаю"],"answerIdx":0},
    {"id":"C1-3","level":"C1","q":"Синонім слова «přesvědčený».","options":["впевнений","наляканий","здивований","злий","Не знаю"],"answerIdx":0},
    {"id":"C1-4","level":"C1","q":"Що означає фраза «vzhledem k tomu, že»?","options":["з огляду на те, що","поки","оскільки","тому","Не знаю"],"answerIdx":0},
    {"id":"C1-5","level":"C1","q":"Що означає слово «záměr»?","options":["намір","причина","помилка","думка","Не знаю"],"answerIdx":0},
    {"id":"C1-6","level":"C1","q":"Оберіть синонім до «účinný».","options":["ефективний","ввічливий","потрібний","небезпечний","Не знаю"],"answerIdx":0},
    {"id":"C1-7","level":"C1","q":"Що означає слово «předpoklad»?","options":["припущення","помилка","правило","результат","Не знаю"],"answerIdx":0},
    {"id":"C1-8","level":"C1","q":"Як перекласти фразу «přijít na to»?","options":["зрозуміти","прийти","пригадати","приїхати","Не знаю"],"answerIdx":0},

    {"id":"C2-1","level":"C2","q":"Як перекласти фразу «z hlediska»?","options":["з точки зору","замість","всупереч","убік","Не знаю"],"answerIdx":0},
    {"id":"C2-2","level":"C2","q":"Що означає слово «neodmyslitelný»?","options":["невід’ємний","зайвий","тимчасовий","можливий","Не знаю"],"answerIdx":0},
    {"id":"C2-3","level":"C2","q":"Що означає слово «období»?","options":["період","можливість","рішення","подія","Не знаю"],"answerIdx":0},
    {"id":"C2-4","level":"C2","q":"Що означає фраза «být na pochybách»?","options":["сумніватися","бути впевненим","бути в дорозі","заплутатись","Не знаю"],"answerIdx":0},
    {"id":"C2-5","level":"C2","q":"Як перекласти «v důsledku»?","options":["внаслідок","через","протягом","замість","Не знаю"],"answerIdx":0},
    {"id":"C2-6","level":"C2","q":"Що означає слово «rozporuplný»?","options":["суперечливий","позитивний","ясний","логічний","Не знаю"],"answerIdx":0},
    {"id":"C2-7","level":"C2","q":"Фраза «být si vědom» означає:","options":["усвідомлювати","боятися","пам’ятати","сумніватися","Не знаю"],"answerIdx":0},
    {"id":"C2-8","level":"C2","q":"Що означає слово «převážně»?","options":["переважно","рідко","іноді","завжди","Не знаю"],"answerIdx":0}
  ]
}
